deidentification/__init__.py
deidentification/deidentification.py
deidentification/deidentification_constants.py
deidentification/deidentify.py
deidentification/file_detection.py
deidentification/normalize_punctuation.py
deidentification/safe_print.py
text_deidentification-1.3.2.dist-info/licenses/LICENSE
text_deidentification-1.3.2.dist-info/METADATA
text_deidentification-1.3.2.dist-info/WHEEL
text_deidentification-1.3.2.dist-info/entry_points.txt
text_deidentification-1.3.2.dist-info/top_level.txt
text_deidentification-1.3.2.dist-info/RECORD
