Metadata-Version: 2.4
Name: text-deidentification
Version: 1.3.2
Summary: A Python module for de-identifying personally identifiable information in text
Home-page: https://github.com/jftuga/deidentification
Author: John Taylor
Author-email: 
Classifier: Development Status :: 5 - Production/Stable
Classifier: Intended Audience :: Developers
Classifier: Intended Audience :: Healthcare Industry
Classifier: Intended Audience :: Legal Industry
Classifier: License :: OSI Approved :: MIT License
Classifier: Natural Language :: English
Classifier: Operating System :: OS Independent
Classifier: Programming Language :: Python :: 3
Classifier: Programming Language :: Python :: 3.10
Classifier: Programming Language :: Python :: 3.11
Classifier: Programming Language :: Python :: 3.12
Classifier: Topic :: Text Processing
Classifier: Topic :: Security
Requires-Python: >=3.10
License-File: LICENSE
Requires-Dist: spacy<4.0.0,>=3.8.3
Requires-Dist: torch<3.0.0,>=2.5.1
Requires-Dist: chardet>=5.2.0
Requires-Dist: veryprettytable>=0.8.1
Dynamic: author
Dynamic: classifier
Dynamic: description
Dynamic: description-content-type
Dynamic: home-page
Dynamic: license-file
Dynamic: requires-dist
Dynamic: requires-python
Dynamic: summary
